anaconda_catalogs/__init__.py
anaconda_catalogs/catalog.py
anaconda_catalogs/exceptions.py
anaconda_catalogs/py.typed
anaconda_catalogs-0.2.0.dist-info/LICENSE
anaconda_catalogs-0.2.0.dist-info/METADATA
anaconda_catalogs-0.2.0.dist-info/WHEEL
anaconda_catalogs-0.2.0.dist-info/entry_points.txt
anaconda_catalogs-0.2.0.dist-info/top_level.txt
anaconda_catalogs-0.2.0.dist-info/RECORD
