Metadata-Version: 2.1
Name: anaconda-catalogs
Version: 0.2.0
Summary: Client library for Anaconda Catalogs
Author-email: Matt Kramer <mkramer@anaconda.com>
License: BSD-3-Clause
Requires-Python: >=3.8
Provides-Extra: dev
Provides-Extra: publish
License-File: LICENSE
